MANIFEST.in
README.md
requirements.txt
setup.py
Hefesto/__init__.py
Hefesto/main.py
Hefesto/template.py
Hefesto.egg-info/PKG-INFO
Hefesto.egg-info/SOURCES.txt
Hefesto.egg-info/dependency_links.txt
Hefesto.egg-info/top_level.txt