Metadata-Version: 1.0
Name: Hefesto
Version: 0.1.7
Summary: Preprocessing datatable toolkit
Home-page: https://github.com/pabloalarconm/hefesto
Author: Pablo Alarcón Moreno
Author-email: pabloalarconmoreno@gmail.com
License: MIT
Keywords: EJP,CDE
Platform: UNKNOWN
